calculos_matematicos_package/__init__.py
calculos_matematicos_package/basico.py
calculos_matematicos_package/intermediario.py
calculos_matematicos_package-0.0.1.dist-info/METADATA
calculos_matematicos_package-0.0.1.dist-info/WHEEL
calculos_matematicos_package-0.0.1.dist-info/top_level.txt
calculos_matematicos_package-0.0.1.dist-info/RECORD
