Metadata-Version: 2.4
Name: calculos_matematicos_package
Version: 0.0.1
Summary: My short description
Home-page: https://github.com/wklamorim/simple-package-template.git
Author: Wilkerson Amorim
Author-email: wklamorim@gmail.com
Requires-Python: >=3.8
Requires-Dist: setuptools~=80.9.0
Dynamic: author
Dynamic: author-email
Dynamic: description
Dynamic: description-content-type
Dynamic: home-page
Dynamic: requires-dist
Dynamic: requires-python
Dynamic: summary
